hebill/__init__.py
hebill/logo.ico
hebill/builtin/__init__.py
hebill/builtin/functions/__init__.py
hebill/builtin/functions/builtins.py
hebill/builtin/functions/builtins.pyi
hebill/builtin/functions/decorators.py
hebill/builtin/functions/decorators.pyi
hebill/builtin/system/__init__.py
hebill/builtin/system/core.py
hebill/builtin/system/core.pyi
hebill/builtin/system/components/__init__.py
hebill/builtin/system/components/core.py
hebill/builtin/system/components/core.pyi
hebill/builtin/system/components/cls_type/__init__.py
hebill/builtin/system/components/cls_type/core.py
hebill/builtin/system/components/cls_type/core.pyi
hebill/builtin/system/components/configs/__init__.py
hebill/builtin/system/components/configs/core.py
hebill/builtin/system/components/configs/core.pyi
hebill/builtin/system/components/configs/defaults/__init__.py
hebill/builtin/system/components/configs/defaults/core.py
hebill/builtin/system/components/configs/defaults/core.pyi
hebill/builtin/system/components/css_maker/__init__.py
hebill/builtin/system/components/css_maker/core.py
hebill/builtin/system/components/css_maker/core.pyi
hebill/builtin/system/components/css_maker/cls/__init__.py
hebill/builtin/system/components/css_maker/cls/core.py
hebill/builtin/system/components/css_maker/cls/core.pyi
hebill/builtin/system/components/css_maker/med/__init__.py
hebill/builtin/system/components/css_maker/med/core.py
hebill/builtin/system/components/css_maker/med/core.pyi
hebill/builtin/system/components/database/__init__.py
hebill/builtin/system/components/database/core.py
hebill/builtin/system/components/database/core.pyi
hebill/builtin/system/components/database/configs/__init__.py
hebill/builtin/system/components/database/configs/core.py
hebill/builtin/system/components/database/configs/core.pyi
hebill/builtin/system/components/database/connection/__init__.py
hebill/builtin/system/components/database/connection/core.py
hebill/builtin/system/components/database/connection/core.pyi
hebill-5.0.5.dist-info/licenses/LICENSE
hebill-5.0.5.dist-info/METADATA
hebill-5.0.5.dist-info/WHEEL
hebill-5.0.5.dist-info/top_level.txt
hebill-5.0.5.dist-info/RECORD
