Metadata-Version: 2.4
Name: hebill
Version: 5.0.5
Summary: Hebill
Author-email: He Bill <hebill@hebill.net>
License-Expression: MIT
Requires-Python: >=3.12
License-File: LICENSE
Requires-Dist: flask>=3.1.2
Requires-Dist: colorama>=0.4.6
Dynamic: license-file
